randtext/__init__.py
randtext/randtext.py
randtext/dictionary/10
randtext/dictionary/11
randtext/dictionary/12
randtext/dictionary/13
randtext/dictionary/14
randtext/dictionary/15
randtext/dictionary/16
randtext/dictionary/17
randtext/dictionary/18
randtext/dictionary/19
randtext/dictionary/2
randtext/dictionary/21
randtext/dictionary/22
randtext/dictionary/23
randtext/dictionary/3
randtext/dictionary/4
randtext/dictionary/5
randtext/dictionary/6
randtext/dictionary/7
randtext/dictionary/8
randtext/dictionary/9
randtext-0.1.3.dist-info/LICENSE
randtext-0.1.3.dist-info/METADATA
randtext-0.1.3.dist-info/WHEEL
randtext-0.1.3.dist-info/top_level.txt
randtext-0.1.3.dist-info/RECORD
