Metadata-Version: 2.1
Name: randtext
Version: 0.1.3
Summary: Generate random text with a considerable amount of control 
Home-page: https://github.com/Mantaseus/randtext
Author: Mantaseus
License: MIT
Platform: UNKNOWN
Classifier: Programming Language :: Python :: 3
Classifier: License :: OSI Approved :: MIT License
Classifier: Operating System :: OS Independent
Requires-Dist: pathlib
